{
  "allowHttpBackend": false,
  "backendCommand": "node backend -c \"tugb191yihmq33b1es8wq8ajqs3qa1\" -s \"/bwZV8evr5xkgYv2ukuuKDk5fC/ePZd2ESKWEZQ4lQo=\" -o \"546623929\"",
  "backendFolderName": "server",
  "certificateExceptions": [],
  "extensionViews": [
    {
      "channelId": "546623929",
      "configurationAnchor": "panel",
      "displayChannelName": "lumawin",
      "features": {
        "isBitsEnabled": false,
        "isChatEnabled": false,
        "isSubscriptionStatusAvailable": false
      },
      "frameSize": {
        "width": 1280,
        "height": 720
      },
      "id": "1",
      "isPopout": false,
      "label": "LumaWin",
      "linked": true,
      "linkedUserId": "546623929",
      "orientation": "Portrait",
      "type": "panel",
      "viewerType": "Logged-In Viewer"
    }
  ],
  "manifest": {
    "anchor": "panel",
    "assetUrls": [],
    "authorName": "LumaWin",
    "bitsEnabled": false,
    "canInstall": true,
    "configUrl": "https://localhost:8080/config.html",
    "configurationLocation": "none",
    "description": "LumaWin Lighting System used to control LED Strips",
    "eulaTosUrl": "",
    "hasChatSupport": false,
    "iconUrl": "",
    "iconUrls": {},
    "id": "tugb191yihmq33b1es8wq8ajqs3qa1",
    "installationCount": -42,
    "liveConfigUrl": "",
    "name": "LumaWin-LightSystem",
    "panelHeight": 300,
    "privacyPolicyUrl": "",
    "requestIdentityLink": false,
    "requiredBroadcasterAbilities": [],
    "screenshotUrls": [],
    "sku": "",
    "state": "Testing",
    "subscriptionsSupportLevel": "none",
    "summary": "LumaWin Lighting System used to control LED Strips",
    "supportEmail": "robertwinslow@comcast.net",
    "vendorCode": "",
    "version": "0.02",
    "viewerSummary": "",
    "viewerUrl": "https://localhost:8080/panel.html",
    "viewerUrls": {
      "panel": "https://localhost:8080/panel.html",
      "component": "https://localhost:8080/video_component.html"
    },
    "views": {
      "panel": {
        "viewerUrl": "https://localhost:8080/panel.html",
        "height": 300,
        "canLinkExternalContent": false
      },
      "component": {
        "viewerUrl": "https://localhost:8080/video_component.html",
        "aspectWidth": 0,
        "aspectHeight": 0,
        "aspectRatioX": 300,
        "aspectRatioY": 200,
        "scalePixels": 1024,
        "targetHeight": 4000,
        "size": 0,
        "zoom": false,
        "zoomPixels": 0,
        "canLinkExternalContent": false,
        "autoScale": true
      },
      "config": {
        "viewerUrl": "https://localhost:8080/config.html",
        "canLinkExternalContent": false
      }
    },
    "whitelistedConfigUrls": [],
    "whitelistedPanelUrls": []
  },
  "frontendCommand": "",
  "frontendFolderName": "/home/hellweek/code/LightsWebpage/LumaWin Extension",
  "name": "LumaWin-LightSystem",
  "version": 2
}